capivara/__init__.py
capivara/api.py
capivara-1.0.1.dist-info/DESCRIPTION.rst
capivara-1.0.1.dist-info/METADATA
capivara-1.0.1.dist-info/RECORD
capivara-1.0.1.dist-info/WHEEL
capivara-1.0.1.dist-info/metadata.json
capivara-1.0.1.dist-info/top_level.txt
