Metadata-Version: 2.0
Name: capivara
Version: 1.0.1
Summary: Generates & Obtain DOM (Document Object Model)
Home-page: https://github.com/raphamorim/capivara
Author: Raphael Amorim
Author-email: rapha850@gmail
License: Apache 2.0
Keywords: dom javascript object model development
Platform: UNKNOWN
Classifier: License :: OSI Approved :: Apache Software License
Classifier: Programming Language :: Python :: 2
Classifier: Programming Language :: Python :: 2.6
Classifier: Programming Language :: Python :: 2.7
Classifier: Programming Language :: Python :: 3
Classifier: Programming Language :: Python :: 3.3
Requires-Dist: nose
